betdaq/__init__.py
betdaq/apiclient.py
betdaq/baseclient.py
betdaq/compat.py
betdaq/enums.py
betdaq/exceptions.py
betdaq/filters.py
betdaq/utils.py
betdaq/classifiers/__init__.py
betdaq/classifiers/betting.py
betdaq/classifiers/marketdata.py
betdaq/endpoints/__init__.py
betdaq/endpoints/account.py
betdaq/endpoints/baseendpoint.py
betdaq/endpoints/betting.py
betdaq/endpoints/marketdata.py
betdaq/endpoints/trading.py
betdaq/errorparsers/__init__.py
betdaq/errorparsers/betting.py
betdaq/errorparsers/marketdata.py
betdaq/resources/__init__.py
betdaq/resources/accountresources.py
betdaq/resources/baseresources.py
betdaq/resources/bettingresources.py
betdaq/resources/marketdataresources.py
betdaq/resources/tradingresources.py
betdaq-0.0.2.dist-info/DESCRIPTION.rst
betdaq-0.0.2.dist-info/METADATA
betdaq-0.0.2.dist-info/RECORD
betdaq-0.0.2.dist-info/WHEEL
betdaq-0.0.2.dist-info/metadata.json
betdaq-0.0.2.dist-info/top_level.txt
