Metadata-Version: 2.0
Name: betdaq
Version: 0.0.2
Summary: Betdaq API Python wrapper
Home-page: https://github.com/rozzac90/betdaq_py
Author: Rory Cole
Author-email: rory.cole1990@gmail.com
License: UNKNOWN
Platform: UNKNOWN
Requires-Dist: python-dateutil (==2.6.0)
Requires-Dist: pytz (==2017.2)
Requires-Dist: requests (==2.13.0)
Requires-Dist: zeep (==2.1.1)
